tokenkit/__init__.py
tokenkit/tokenkit.py
tokenkit-0.1.3.dist-info/licenses/LICENSE
tokenkit-0.1.3.dist-info/METADATA
tokenkit-0.1.3.dist-info/WHEEL
tokenkit-0.1.3.dist-info/top_level.txt
tokenkit-0.1.3.dist-info/RECORD
