Metadata-Version: 2.4
Name: tokenkit
Version: 0.1.3
Summary: Calculate and visualize fertility and parity metrics for tokenizers
Author: Ada Zhang, Nihal Karim, Hamza Louzan, Victor Wei, Cody Carroll, Jessica Lundin
Author-email: Ada Zhang <abz200026@gmail.com>
License: MIT
Requires-Python: >=3.8
License-File: LICENSE
Requires-Dist: transformers
Requires-Dist: pandas
Requires-Dist: matplotlib
Requires-Dist: numpy
Provides-Extra: dev
Requires-Dist: pytest; extra == "dev"
Dynamic: license-file
